cm_platform_library/__init__.py
cm_platform_library/conn.py
cm_platform_library/models.py
cm_platform_library/actions/__init__.py
cm_platform_library/actions/licenses.py
cm_platform_library/actions/providers.py
cm_platform_library/actions/requests.py
cm_platform_library-0.0.9.dist-info/METADATA
cm_platform_library-0.0.9.dist-info/WHEEL
cm_platform_library-0.0.9.dist-info/top_level.txt
cm_platform_library-0.0.9.dist-info/RECORD
