Metadata-Version: 2.1
Name: cm-platform-library
Version: 0.0.9
Summary: Handles our platform and authentication requests
Home-page: https://gitlab.com/cloudmicro/pypi/cm_platform_library
Author: Trent Murray
Author-email: trent@cloudmicro.io
License: UNKNOWN
Platform: UNKNOWN
Classifier: Programming Language :: Python :: 3
Classifier: License :: OSI Approved :: MIT License
Classifier: Operating System :: OS Independent
Requires-Dist: sqlalchemy
Requires-Dist: cm-service-library
Requires-Dist: psycopg2-binary
Requires-Dist: databases[postgresql]
